[
    {
        "profit": 754489202423,
        "isRealName": false,
        "name": "Heavy-Autumn-Wolf"
    },
    {
        "profit": 715436744965,
        "isRealName": false,
        "name": "Quick-Grove-Mind"
    },
    {
        "profit": 693745996173,
        "isRealName": false,
        "name": "Mercury-Wood-Sprite"
    },
    {
        "profit": 524468412368,
        "isRealName": true,
        "name": "Alameda Research"
    },
    {
        "profit": 421651590744,
        "isRealName": false,
        "name": "Hot-Relic-Fancier"
    },
    {
        "profit": 231547097967,
        "isRealName": false,
        "name": "Skitter-Peridot-Raven"
    },
    {
        "profit": 192279358652,
        "isRealName": true,
        "name": "coincidentcapitalltd"
    },
    {
        "profit": 186960576319,
        "isRealName": false,
        "name": "Jade-Platinum-Legs"
    },
    {
        "profit": 186331803764,
        "isRealName": false,
        "name": "Paper-Feather-Stallion"
    },
    {
        "profit": 176682942952,
        "isRealName": false,
        "name": "Honeysuckle-South-Rib"
    },
    {
        "profit": 176454784734,
        "isRealName": true,
        "name": "Roger_Leotank"
    },
    {
        "profit": 176170772583,
        "isRealName": true,
        "name": "AK is fraud"
    },
    {
        "profit": 169848422787,
        "isRealName": false,
        "name": "Tree-Surf-Dragon"
    },
    {
        "profit": 169670395643,
        "isRealName": true,
        "name": "alamedaresearchltd@gmail.com"
    },
    {
        "profit": 161963821540,
        "isRealName": true,
        "name": "Circle_Trade"
    },
    {
        "profit": 152041246585,
        "isRealName": false,
        "name": "Jelly-Mint-Flier"
    },
    {
        "profit": 151548748328,
        "isRealName": true,
        "name": "xorq"
    },
    {
        "profit": 151460670388,
        "isRealName": true,
        "name": "daniel3"
    },
    {
        "profit": 147637986659,
        "isRealName": false,
        "name": "Cream-White-Ox"
    },
    {
        "profit": 139124293569,
        "isRealName": false,
        "name": "Cedar-Spice-Fisher"
    },
    {
        "profit": 137238014935,
        "isRealName": false,
        "name": "Quill-Rift-Hoof"
    },
    {
        "profit": 121855770779,
        "isRealName": false,
        "name": "Denim-Sun-Speaker"
    },
    {
        "profit": 119484468513,
        "isRealName": false,
        "name": "Big-Rift-Sting"
    },
    {
        "profit": 117203562217,
        "isRealName": false,
        "name": "Leather-Metal-Razor"
    },
    {
        "profit": 115164617038,
        "isRealName": true,
        "name": "Linen"
    }
]