[
    {
        "profit": 749530149193,
        "isRealName": false,
        "name": "Heavy-Autumn-Wolf"
    },
    {
        "profit": 565952993276,
        "isRealName": false,
        "name": "Quick-Grove-Mind"
    },
    {
        "profit": 532235334655,
        "isRealName": false,
        "name": "Mercury-Wood-Sprite"
    },
    {
        "profit": 523872797255,
        "isRealName": true,
        "name": "Alameda Research"
    },
    {
        "profit": 421630669888,
        "isRealName": false,
        "name": "Hot-Relic-Fancier"
    },
    {
        "profit": 202025604478,
        "isRealName": false,
        "name": "Jade-Platinum-Legs"
    },
    {
        "profit": 177180269909,
        "isRealName": false,
        "name": "Skitter-Peridot-Raven"
    },
    {
        "profit": 176454784734,
        "isRealName": true,
        "name": "Roger_Leotank"
    },
    {
        "profit": 168746706938,
        "isRealName": true,
        "name": "alamedaresearchltd@gmail.com"
    },
    {
        "profit": 158710162895,
        "isRealName": false,
        "name": "Honeysuckle-South-Rib"
    },
    {
        "profit": 155903080327,
        "isRealName": true,
        "name": "AK is fraud"
    },
    {
        "profit": 153676533466,
        "isRealName": false,
        "name": "Paper-Feather-Stallion"
    },
    {
        "profit": 152945860191,
        "isRealName": false,
        "name": "Silent-Hurricane-Guardian"
    },
    {
        "profit": 148536165862,
        "isRealName": false,
        "name": "Cream-White-Ox"
    },
    {
        "profit": 140432592819,
        "isRealName": false,
        "name": "Tree-Surf-Dragon"
    },
    {
        "profit": 137924031451,
        "isRealName": false,
        "name": "Leather-Metal-Razor"
    },
    {
        "profit": 136802023621,
        "isRealName": false,
        "name": "Cedar-Spice-Fisher"
    },
    {
        "profit": 121855770779,
        "isRealName": false,
        "name": "Denim-Sun-Speaker"
    },
    {
        "profit": 120473405440,
        "isRealName": false,
        "name": "Noble-Black-Antelope"
    },
    {
        "profit": 119551208760,
        "isRealName": true,
        "name": "daniel3"
    },
    {
        "profit": 113631256750,
        "isRealName": true,
        "name": "Linen"
    },
    {
        "profit": 113597723388,
        "isRealName": false,
        "name": "Big-Rift-Sting"
    },
    {
        "profit": 107677258872,
        "isRealName": false,
        "name": "Wave-Apple-Puma"
    }
]